README.md
setup.cfg
setup.py
events/__init__.py
events/baseobject.py
events/event.py
events/eventhandler.py
events/logger.py
events/publisher.py
events/subscriber.py
events_jimobama.egg-info/PKG-INFO
events_jimobama.egg-info/SOURCES.txt
events_jimobama.egg-info/dependency_links.txt
events_jimobama.egg-info/top_level.txt