Metadata-Version: 2.1
Name: events-jimobama
Version: 0.0.1
Summary: C# like event handler (pubsub)
Home-page: https://github.com/miljimo/events.git
Author: Obaro I. Johnson
Author-email: johnson.obaro@hotmail.com
License: UNKNOWN
Platform: UNKNOWN
Classifier: Programming Language :: Python :: 3
Classifier: License :: OSI Approved :: MIT License
Classifier: Operating System :: OS Independent
Requires-Python: >=3.6
